aware_environment/__init__.py
aware_environment/acl.py
aware_environment/environment.py
aware_environment/exceptions.py
aware_environment/frontmatter.py
aware_environment/locks.py
aware_environment/panel.py
aware_environment/pathspec.py
aware_environment/renderer.py
aware_environment/seed.py
aware_environment/agent/registry.py
aware_environment/agent/spec.py
aware_environment/doc/__init__.py
aware_environment/doc/fragments.py
aware_environment/doc/markers.py
aware_environment/fs/__init__.py
aware_environment/fs/core.py
aware_environment/fs/receipt.py
aware_environment/object/arguments.py
aware_environment/object/metadata.py
aware_environment/object/registry.py
aware_environment/object/spec.py
aware_environment/protocol/__init__.py
aware_environment/protocol/registry.py
aware_environment/protocol/renderer.py
aware_environment/protocol/spec.py
aware_environment/role/registry.py
aware_environment/role/spec.py
aware_environment/rule/registry.py
aware_environment/rule/spec.py
aware_environment/runtime/__init__.py
aware_environment/runtime/command_renderer.py
aware_environment/runtime/executor.py
aware_environment/runtime/function_call_request_builder.py
aware_environment/summary/__init__.py
aware_environment-0.1.3.dist-info/METADATA
aware_environment-0.1.3.dist-info/WHEEL
aware_environment-0.1.3.dist-info/licenses/LICENSE
aware_environment-0.1.3.dist-info/RECORD
