Metadata-Version: 2.4
Name: aware-environment
Version: 0.1.3
Summary: Contracts and runtime helpers for Aware environments (agents, roles, rules, objects).
Project-URL: Homepage, https://pypi.org/project/aware-environment/
Project-URL: Source, https://github.com/aware-network/aware-sdk
Project-URL: Documentation, https://github.com/aware-network/aware-sdk/tree/main/libs/environment/README.md
Project-URL: Changelog, https://github.com/aware-network/aware-sdk/tree/main/libs/environment/CHANGELOG.md
Project-URL: Issues, https://github.com/aware-network/aware-sdk/issues
Author: AWARE Team
License: MIT License
License-File: LICENSE
Keywords: agents,automation,aware,environment,rules
Classifier: Intended Audience :: Developers
Classifier: License :: OSI Approved :: MIT License
Classifier: Operating System :: OS Independent
Classifier: Programming Language :: Python :: 3
Classifier: Programming Language :: Python :: 3.12
Requires-Python: >=3.12
Requires-Dist: pyyaml<7.0.0,>=6.0.2
Provides-Extra: test
Requires-Dist: pytest>=8.4.2; extra == 'test'
